ScrapeSearchEngine/ScrapeSearchEngine.py
ScrapeSearchEngine/SearchEngine.py
scrape_search_engine-0.2.2.dist-info/LICENSE
scrape_search_engine-0.2.2.dist-info/METADATA
scrape_search_engine-0.2.2.dist-info/WHEEL
scrape_search_engine-0.2.2.dist-info/top_level.txt
scrape_search_engine-0.2.2.dist-info/RECORD
