Metadata-Version: 2.1
Name: scrape-search-engine
Version: 0.2.2
Summary: Search anything on the different Search Engine's it will collect all the links.
Home-page: https://github.com/sujitmandal/scrape-search-engine
Author: Sujit Mandal
Author-email: mandals974@gmail.com
License: MIT
Platform: UNKNOWN
Classifier: License :: OSI Approved :: MIT License
Classifier: Programming Language :: Python :: 2.7
Classifier: Programming Language :: Python :: 3.0
Classifier: Programming Language :: Python :: 3.5
Classifier: Programming Language :: Python :: 3.6
Classifier: Programming Language :: Python :: 3.7
Classifier: Programming Language :: Python :: 3.8
Classifier: Programming Language :: Python :: 3.9
